<?xml version="1.0" encoding="utf-8"?>
<HomeStats>
  <Player>
    <PlayerId>29</PlayerId>
    <PlayerName>SADA, VICTOR</PlayerName>
    <PlayerNo>8</PlayerNo>
    <TwoPMissed>1</TwoPMissed>
    <TwoPMade>3</TwoPMade>
    <ThreePMissed>0</ThreePMissed>
    <ThreePMade>0</ThreePMade>
    <Assist>0</Assist>
    <Turnover>0</Turnover>
    <DefRebound>0</DefRebound>
    <OffRebound>0</OffRebound>
    <Steal>0</Steal>
    <FoulOn>0</FoulOn>
    <Foul>0</Foul>
    <FTMissed>0</FTMissed>
    <FTMade>0</FTMade>
    <Block>0</Block>
    <BlockAgainst>0</BlockAgainst>
    <UnsportsmanFoul>0</UnsportsmanFoul>
    <MinutesPlayed>1200</MinutesPlayed>
  </Player>
  <Player>
    <PlayerId>30</PlayerId>
    <PlayerName>HUERTAS, MARCELINHO</PlayerName>
    <PlayerNo>9</PlayerNo>
    <TwoPMissed>3</TwoPMissed>
    <TwoPMade>1</TwoPMade>
    <ThreePMissed>0</ThreePMissed>
    <ThreePMade>0</ThreePMade>
    <Assist>1</Assist>
    <Turnover>0</Turnover>
    <DefRebound>1</DefRebound>
    <OffRebound>1</OffRebound>
    <Steal>0</Steal>
    <FoulOn>0</FoulOn>
    <Foul>2</Foul>
    <FTMissed>0</FTMissed>
    <FTMade>0</FTMade>
    <Block>0</Block>
    <BlockAgainst>0</BlockAgainst>
    <UnsportsmanFoul>0</UnsportsmanFoul>
    <MinutesPlayed>1559</MinutesPlayed>
  </Player>
  <Player>
    <PlayerId>31</PlayerId>
    <PlayerName> ABRINES, ALEJANDRO</PlayerName>
    <PlayerNo>10</PlayerNo>
    <TwoPMissed>1</TwoPMissed>
    <TwoPMade>2</TwoPMade>
    <ThreePMissed>1</ThreePMissed>
    <ThreePMade>0</ThreePMade>
    <Assist>0</Assist>
    <Turnover>0</Turnover>
    <DefRebound>1</DefRebound>
    <OffRebound>1</OffRebound>
    <Steal>0</Steal>
    <FoulOn>0</FoulOn>
    <Foul>0</Foul>
    <FTMissed>0</FTMissed>
    <FTMade>0</FTMade>
    <Block>0</Block>
    <BlockAgainst>0</BlockAgainst>
    <UnsportsmanFoul>0</UnsportsmanFoul>
    <MinutesPlayed>686</MinutesPlayed>
  </Player>
  <Player>
    <PlayerId>32</PlayerId>
    <PlayerName> NAVARRO, JUAN CARLOS</PlayerName>
    <PlayerNo>11</PlayerNo>
    <TwoPMissed>2</TwoPMissed>
    <TwoPMade>5</TwoPMade>
    <ThreePMissed>2</ThreePMissed>
    <ThreePMade>5</ThreePMade>
    <Assist>0</Assist>
    <Turnover>4</Turnover>
    <DefRebound>1</DefRebound>
    <OffRebound>1</OffRebound>
    <Steal>1</Steal>
    <FoulOn>0</FoulOn>
    <Foul>2</Foul>
    <FTMissed>0</FTMissed>
    <FTMade>0</FTMade>
    <Block>0</Block>
    <BlockAgainst>0</BlockAgainst>
    <UnsportsmanFoul>0</UnsportsmanFoul>
    <MinutesPlayed>1645</MinutesPlayed>
  </Player>
  <Player>
    <PlayerId>33</PlayerId>
    <PlayerName> JASIKEVICIUS, SARUNAS</PlayerName>
    <PlayerNo>13</PlayerNo>
    <TwoPMissed>0</TwoPMissed>
    <TwoPMade>0</TwoPMade>
    <ThreePMissed>0</ThreePMissed>
    <ThreePMade>0</ThreePMade>
    <Assist>0</Assist>
    <Turnover>0</Turnover>
    <DefRebound>0</DefRebound>
    <OffRebound>0</OffRebound>
    <Steal>0</Steal>
    <FoulOn>0</FoulOn>
    <Foul>0</Foul>
    <FTMissed>0</FTMissed>
    <FTMade>0</FTMade>
    <Block>0</Block>
    <BlockAgainst>0</BlockAgainst>
    <UnsportsmanFoul>0</UnsportsmanFoul>
    <MinutesPlayed>0</MinutesPlayed>
  </Player>
  <Player>
    <PlayerId>34</PlayerId>
    <PlayerName> TODOROVIC, MARKO</PlayerName>
    <PlayerNo>14</PlayerNo>
    <TwoPMissed>2</TwoPMissed>
    <TwoPMade>1</TwoPMade>
    <ThreePMissed>0</ThreePMissed>
    <ThreePMade>0</ThreePMade>
    <Assist>0</Assist>
    <Turnover>1</Turnover>
    <DefRebound>2</DefRebound>
    <OffRebound>0</OffRebound>
    <Steal>0</Steal>
    <FoulOn>5</FoulOn>
    <Foul>0</Foul>
    <FTMissed>0</FTMissed>
    <FTMade>2</FTMade>
    <Block>0</Block>
    <BlockAgainst>0</BlockAgainst>
    <UnsportsmanFoul>0</UnsportsmanFoul>
    <MinutesPlayed>755</MinutesPlayed>
  </Player>
  <Player>
    <PlayerId>37</PlayerId>
    <PlayerName> RABASEDA, XAVIER</PlayerName>
    <PlayerNo>22</PlayerNo>
    <TwoPMissed>4</TwoPMissed>
    <TwoPMade>1</TwoPMade>
    <ThreePMissed>2</ThreePMissed>
    <ThreePMade>1</ThreePMade>
    <Assist>1</Assist>
    <Turnover>0</Turnover>
    <DefRebound>1</DefRebound>
    <OffRebound>1</OffRebound>
    <Steal>0</Steal>
    <FoulOn>0</FoulOn>
    <Foul>0</Foul>
    <FTMissed>0</FTMissed>
    <FTMade>0</FTMade>
    <Block>0</Block>
    <BlockAgainst>0</BlockAgainst>
    <UnsportsmanFoul>0</UnsportsmanFoul>
    <MinutesPlayed>1114</MinutesPlayed>
  </Player>
  <Player>
    <PlayerId>38</PlayerId>
    <PlayerName> HEZONJA, MARIO</PlayerName>
    <PlayerNo>23</PlayerNo>
    <TwoPMissed>0</TwoPMissed>
    <TwoPMade>2</TwoPMade>
    <ThreePMissed>0</ThreePMissed>
    <ThreePMade>0</ThreePMade>
    <Assist>0</Assist>
    <Turnover>0</Turnover>
    <DefRebound>1</DefRebound>
    <OffRebound>1</OffRebound>
    <Steal>0</Steal>
    <FoulOn>3</FoulOn>
    <Foul>0</Foul>
    <FTMissed>1</FTMissed>
    <FTMade>1</FTMade>
    <Block>0</Block>
    <BlockAgainst>0</BlockAgainst>
    <UnsportsmanFoul>0</UnsportsmanFoul>
    <MinutesPlayed>755</MinutesPlayed>
  </Player>
  <Player>
    <PlayerId>192</PlayerId>
    <PlayerName> OLESON, BRAD</PlayerName>
    <PlayerNo>24</PlayerNo>
    <TwoPMissed>2</TwoPMissed>
    <TwoPMade>5</TwoPMade>
    <ThreePMissed>1</ThreePMissed>
    <ThreePMade>2</ThreePMade>
    <Assist>1</Assist>
    <Turnover>1</Turnover>
    <DefRebound>1</DefRebound>
    <OffRebound>1</OffRebound>
    <Steal>2</Steal>
    <FoulOn>2</FoulOn>
    <Foul>0</Foul>
    <FTMissed>1</FTMissed>
    <FTMade>1</FTMade>
    <Block>0</Block>
    <BlockAgainst>0</BlockAgainst>
    <UnsportsmanFoul>0</UnsportsmanFoul>
    <MinutesPlayed>1200</MinutesPlayed>
  </Player>
  <Player>
    <PlayerId>39</PlayerId>
    <PlayerName> LORBEK, ERAZEM</PlayerName>
    <PlayerNo>25</PlayerNo>
    <TwoPMissed>1</TwoPMissed>
    <TwoPMade>7</TwoPMade>
    <ThreePMissed>6</ThreePMissed>
    <ThreePMade>0</ThreePMade>
    <Assist>2</Assist>
    <Turnover>0</Turnover>
    <DefRebound>3</DefRebound>
    <OffRebound>3</OffRebound>
    <Steal>0</Steal>
    <FoulOn>1</FoulOn>
    <Foul>0</Foul>
    <FTMissed>1</FTMissed>
    <FTMade>1</FTMade>
    <Block>2</Block>
    <BlockAgainst>0</BlockAgainst>
    <UnsportsmanFoul>0</UnsportsmanFoul>
    <MinutesPlayed>1286</MinutesPlayed>
  </Player>
  <Player>
    <PlayerId>42</PlayerId>
    <PlayerName> MBAYE, PAPA</PlayerName>
    <PlayerNo>34</PlayerNo>
    <TwoPMissed>0</TwoPMissed>
    <TwoPMade>0</TwoPMade>
    <ThreePMissed>0</ThreePMissed>
    <ThreePMade>0</ThreePMade>
    <Assist>0</Assist>
    <Turnover>0</Turnover>
    <DefRebound>0</DefRebound>
    <OffRebound>0</OffRebound>
    <Steal>0</Steal>
    <FoulOn>0</FoulOn>
    <Foul>0</Foul>
    <FTMissed>0</FTMissed>
    <FTMade>0</FTMade>
    <Block>0</Block>
    <BlockAgainst>0</BlockAgainst>
    <UnsportsmanFoul>0</UnsportsmanFoul>
    <MinutesPlayed>155</MinutesPlayed>
  </Player>
  <Player>
    <PlayerId>43</PlayerId>
    <PlayerName> TOMIC, ANTE</PlayerName>
    <PlayerNo>44</PlayerNo>
    <TwoPMissed>2</TwoPMissed>
    <TwoPMade>2</TwoPMade>
    <ThreePMissed>1</ThreePMissed>
    <ThreePMade>0</ThreePMade>
    <Assist>2</Assist>
    <Turnover>0</Turnover>
    <DefRebound>1</DefRebound>
    <OffRebound>1</OffRebound>
    <Steal>0</Steal>
    <FoulOn>0</FoulOn>
    <Foul>0</Foul>
    <FTMissed>0</FTMissed>
    <FTMade>0</FTMade>
    <Block>0</Block>
    <BlockAgainst>0</BlockAgainst>
    <UnsportsmanFoul>0</UnsportsmanFoul>
    <MinutesPlayed>1645</MinutesPlayed>
  </Player>
  <HomeTeam>
    <HomeTeamId>2</HomeTeamId>
    <HomeTeamName>BARCELONA</HomeTeamName>
    <TimeOut>3</TimeOut>
    <FastbreaksMade>2</FastbreaksMade>
    <FastbreaksMissed>2</FastbreaksMissed>
    <IPERIOD>21</IPERIOD>
    <IIPERIOD>38</IIPERIOD>
    <IIIPERIOD>63</IIIPERIOD>
    <IVPERIOD>87</IVPERIOD>
  </HomeTeam>
  <GameInfo>
    <CTime>0</CTime>
    <CPeriod>FINAL SCORE</CPeriod>
    <CScore>87-76</CScore>
    <GameId>32</GameId>
  </GameInfo>
  <CoordinatesHome>
    <XYText>2 75 73*3 83 61*2 60 47*5 208 138*2 69 57*3 150 37*2 106 58*3 192 63*4 43 117*4 207 146*3 81 64*5 28 100*3 186 40*4 103 158*3 168 27*4 38 110*3 208 38*2 76 36*2 89 47*3 74 32*2 106 52*3 84 59*2 54 25*3 57 42*2 61 64*4 124 154*3 50 37*3 84 84*2 127 81*3 53 57*4 49 126*3 147 105*5 33 80*4 18 92*4 43 114*4 131 163*3 105 53*3 61 60*4 160 155*3 126 27*2 101 33*4 91 151*3 103 45*3 65 67*3 119 111*4 34 84*3 69 60*5 242 81*2 121 30*2 88 54*3 58 40*2 74 20*3 119 21*3 123 49*5 53 120*2 65 35*5 203 141*3 119 32*2 107 71*5 241 106*4 39 117*3 49 32*3 67 37*3 78 14*5 29 105*2 56 45*2 201 23*3 89 22*</XYText>
  </CoordinatesHome>
  <Event>
    <EventSText>I PERIOD*10:00-BAR-Change : 9 --11 -24 -25 -44 *10:00-MAC-Change : 4 --5 --6 --7 --9 -*09:55-BAR-9 - HUERTAS, MARCELINHO-Missed 2P*09:49-MAC-6 - SMITH, DEVIN-Def Rebound*09:46-MAC-6 - SMITH, DEVIN-Missed 2P*09:43-MAC-7 - HICKMAN, RICKY-Off Rebound*09:40-MAC-7 - HICKMAN, RICKY-Foul*09:40-MAC-7 - HICKMAN, RICKY-Foul*09:36-BAR-9 - HUERTAS, MARCELINHO-Foul*09:36-BAR-9 - HUERTAS, MARCELINHO-Foul*09:31-MAC-7 - HICKMAN, RICKY-Free Throw Missed*09:31-MAC-7 - HICKMAN, RICKY-Free Throw Made*09:25-BAR-11 - NAVARRO, JUAN CARLOS-Made 2P*09:20-BAR-25 - LORBEK, ERAZEM-Assist*09:17-MAC-4 - LOGAN, DAVID-Assist*09:15-MAC-7 - HICKMAN, RICKY-Made 2P*09:08-BAR-25 - LORBEK, ERAZEM-Missed 2P*09:05-MAC-6 - SMITH, DEVIN-Def Rebound*09:02-MAC-Fastbreak Made*09:01-MAC-6 - SMITH, DEVIN-Assist*08:59-MAC-4 - LOGAN, DAVID-Made 2P*08:51-BAR-11 - NAVARRO, JUAN CARLOS-Made 3P*08:48-BAR-44 - TOMIC, ANTE-Assist*07:40-MAC-5 - JAMES, SHAWN-Turnover*07:38-BAR-24 - OLESON, BRAD-Steal*07:34-BAR-11 - NAVARRO, JUAN CARLOS-Turnover*07:32-MAC-6 - SMITH, DEVIN-Turnover*07:30-MAC-6 - SMITH, DEVIN-Steal*07:27-BAR-9 - HUERTAS, MARCELINHO-Missed 2P*07:23-BAR-25 - LORBEK, ERAZEM-Off Rebound*07:22-BAR-25 - LORBEK, ERAZEM-Made 2P*06:16-MAC-9 - ROTH, MORAN-Made 2P*06:13-BAR-44 - TOMIC, ANTE-Missed 2P*06:10-MAC-7 - HICKMAN, RICKY-Def Rebound*06:09-MAC-7 - HICKMAN, RICKY-Assist*06:06-MAC-5 - JAMES, SHAWN-Made 2P*06:04-MAC-Fastbreak Made*06:03-MAC-Time Out*04:58-BAR-24 - OLESON, BRAD-Made 2P*04:56-BAR-Time Out*04:54-MAC-7 - HICKMAN, RICKY-Missed 2P*04:51-BAR-44 - TOMIC, ANTE-Def Rebound*04:49-BAR-44 - TOMIC, ANTE-Missed 3P*04:43-BAR-11 - NAVARRO, JUAN CARLOS-Off Rebound*04:42-BAR-11 - NAVARRO, JUAN CARLOS-Missed 3P*04:38-MAC-6 - SMITH, DEVIN-Def Rebound*04:31-MAC-6 - SMITH, DEVIN-Foul On*04:31-MAC-6 - SMITH, DEVIN-Foul On*04:27-BAR-11 - NAVARRO, JUAN CARLOS-Foul*04:27-BAR-11 - NAVARRO, JUAN CARLOS-Foul*04:14-MAC-6 - SMITH, DEVIN-Free Throw Made*04:14-MAC-6 - SMITH, DEVIN-Free Throw Made*03:09-BAR-24 - OLESON, BRAD-Made 2P*03:02-MAC-5 - JAMES, SHAWN-Missed 2P*02:59-BAR-24 - OLESON, BRAD-Off Rebound*02:57-BAR-24 - OLESON, BRAD-Foul On*02:54-BAR-24 - OLESON, BRAD-Foul On*02:50-MAC-4 - LOGAN, DAVID-Foul*02:50-MAC-4 - LOGAN, DAVID-Foul*02:46-BAR-24 - OLESON, BRAD-Free Throw Missed*02:45-BAR-24 - OLESON, BRAD-Free Throw Made*02:41-MAC-4 - LOGAN, DAVID-Made 2P*01:34-BAR-11 - NAVARRO, JUAN CARLOS-Made 3P*01:31-BAR-25 - LORBEK, ERAZEM-Assist*01:29-MAC-5 - JAMES, SHAWN-Turnover*01:24-BAR-25 - LORBEK, ERAZEM-Made 2P*01:22-BAR-Fastbreak Made*01:21-BAR-Time Out*01:20-BAR-24 - OLESON, BRAD-Assist*00:54-MAC-6 - SMITH, DEVIN-Missed 2P*00:51-BAR-24 - OLESON, BRAD-Missed 3P*00:48-MAC-5 - JAMES, SHAWN-Def Rebound*00:46-MAC-5 - JAMES, SHAWN-Made 2P*00:37-BAR-25 - LORBEK, ERAZEM-Made 2P*00:27-MAC-4 - LOGAN, DAVID-Made 2P*00:24-MAC-6 - SMITH, DEVIN-Assist*00:13-BAR-25 - LORBEK, ERAZEM-Missed 3P*00:10-BAR-9 - HUERTAS, MARCELINHO-Off Rebound*00:03-BAR-9 - HUERTAS, MARCELINHO-Made 2P*II PERIOD*10:00-BAR-Change : 8 --10 -14 -22 -23 *10:00-MAC-Change : 8 --10 -12 -21 -22 *09:57-BAR-14 - TODOROVIC, MARKO-Missed 2P*09:55-MAC-12 - OHAYON, YOGEV-Made 2P*09:51-BAR-14 - TODOROVIC, MARKO-Turnover*09:48-MAC-10 - PNINI, GUY-Steal*09:46-MAC-10 - PNINI, GUY-Assist*09:45-MAC-Fastbreak Made*09:43-MAC-12 - OHAYON, YOGEV-Made 2P*09:41-BAR-22 - RABASEDA, XAVIER-Missed 2P*09:39-MAC-12 - OHAYON, YOGEV-Def Rebound*09:36-MAC-12 - OHAYON, YOGEV-Off Rebound*09:36-MAC-12 - OHAYON, YOGEV-Off Rebound*09:34-MAC-21 - LANDESBERG, SYLVEN-Missed 2P*09:33-MAC-21 - LANDESBERG, SYLVEN-Missed 2P*09:31-MAC-12 - OHAYON, YOGEV-Made 3P*08:02-BAR-23 - HEZONJA, MARIO-Made 2P*07:59-MAC-21 - LANDESBERG, SYLVEN-Missed 2P*07:57-BAR-23 - HEZONJA, MARIO-Def Rebound*07:51-BAR-14 - TODOROVIC, MARKO-Missed 2P*07:49-MAC-12 - OHAYON, YOGEV-Def Rebound*07:48-MAC-12 - OHAYON, YOGEV-Missed 2P*07:45-BAR-14 - TODOROVIC, MARKO-Def Rebound*06:37-BAR-14 - TODOROVIC, MARKO-Foul On*06:37-BAR-14 - TODOROVIC, MARKO-Foul On*06:36-BAR-14 - TODOROVIC, MARKO-Foul On*06:32-MAC-8 - ELIYAHU, LIOR-Foul*06:32-MAC-8 - ELIYAHU, LIOR-Foul*06:31-MAC-8 - ELIYAHU, LIOR-Foul*06:26-BAR-23 - HEZONJA, MARIO-Foul On*06:25-BAR-23 - HEZONJA, MARIO-Foul On*06:25-BAR-23 - HEZONJA, MARIO-Foul On*06:21-MAC-22 - ZALMANSON, IDAN-Foul*06:21-MAC-22 - ZALMANSON, IDAN-Foul*06:20-MAC-22 - ZALMANSON, IDAN-Foul*06:13-BAR-23 - HEZONJA, MARIO-Free Throw Missed*06:12-BAR-23 - HEZONJA, MARIO-Free Throw Made*06:05-MAC-10 - PNINI, GUY-Made 2P*06:00-BAR-14 - TODOROVIC, MARKO-Made 2P*04:25-MAC-12 - OHAYON, YOGEV-Made 3P*04:23-MAC-21 - LANDESBERG, SYLVEN-Assist*04:20-BAR-8 - SADA, VICTOR-Missed 2P*04:17-MAC-12 - OHAYON, YOGEV-Def Rebound*04:16-MAC-12 - OHAYON, YOGEV-Made 2P*04:11-BAR-10 - ABRINES, ALEJANDRO-Made 2P*04:08-MAC-12 - OHAYON, YOGEV-Missed 2P*04:07-MAC-12 - OHAYON, YOGEV-Def Rebound*04:04-BAR-14 - TODOROVIC, MARKO-Def Rebound*03:59-BAR-10 - ABRINES, ALEJANDRO-Missed 2P*03:55-BAR-10 - ABRINES, ALEJANDRO-Off Rebound*03:52-BAR-10 - ABRINES, ALEJANDRO-Missed 3P*03:49-MAC-21 - LANDESBERG, SYLVEN-Made 2P*02:39-BAR-8 - SADA, VICTOR-Made 2P*02:34-MAC-10 - PNINI, GUY-Made 2P*02:30-MAC-21 - LANDESBERG, SYLVEN-Assist*02:26-MAC-10 - PNINI, GUY-Foul*02:26-MAC-10 - PNINI, GUY-Foul*02:21-BAR-14 - TODOROVIC, MARKO-Foul On*02:21-BAR-14 - TODOROVIC, MARKO-Foul On*02:20-BAR-14 - TODOROVIC, MARKO-Free Throw Made*02:19-BAR-14 - TODOROVIC, MARKO-Free Throw Made*02:14-MAC-Fastbreak Missed*02:12-MAC-12 - OHAYON, YOGEV-Turnover*01:46-BAR-10 - ABRINES, ALEJANDRO-Made 2P*01:42-MAC-22 - ZALMANSON, IDAN-Made 2P*01:39-MAC-10 - PNINI, GUY-Assist*01:37-BAR-22 - RABASEDA, XAVIER-Missed 2P*01:34-BAR-23 - HEZONJA, MARIO-Made 2P*01:33-BAR-23 - HEZONJA, MARIO-Off Rebound*01:31-MAC-12 - OHAYON, YOGEV-Missed 3P*01:29-BAR-10 - ABRINES, ALEJANDRO-Def Rebound*01:26-BAR-22 - RABASEDA, XAVIER-Missed 3P*00:20-MAC-10 - PNINI, GUY-Made 2P*00:05-BAR-8 - SADA, VICTOR-Made 2P*III PERIOD*10:00-BAR-Change : 14 -23 -24 -25 -34 *10:00-MAC-Change : 4 --6 --9 --13 -22 *09:57-BAR-24 - OLESON, BRAD-Made 3P*09:51-MAC-13 - PLANINIC, DARKO-Made 2P*09:49-BAR-25 - LORBEK, ERAZEM-Missed 3P*09:46-BAR-25 - LORBEK, ERAZEM-Off Rebound*09:45-BAR-25 - LORBEK, ERAZEM-Missed 3P*09:44-BAR-25 - LORBEK, ERAZEM-Off Rebound*09:42-BAR-25 - LORBEK, ERAZEM-Missed 3P*09:40-MAC-13 - PLANINIC, DARKO-Def Rebound*09:39-MAC-13 - PLANINIC, DARKO-Turnover*09:36-BAR-24 - OLESON, BRAD-Steal*09:35-BAR-24 - OLESON, BRAD-Turnover*09:33-MAC-9 - ROTH, MORAN-Steal*09:33-MAC-9 - ROTH, MORAN-Turnover*09:29-BAR-24 - OLESON, BRAD-Made 2P*07:25-BAR-Change : 9 --11 -24 -25 -44 *07:22-MAC-4 - LOGAN, DAVID-Made 2P*07:19-BAR-24 - OLESON, BRAD-Made 2P*07:16-MAC-9 - ROTH, MORAN-Missed 2P*07:12-BAR-25 - LORBEK, ERAZEM-Def Rebound*07:11-BAR-25 - LORBEK, ERAZEM-Missed 3P*07:08-MAC-13 - PLANINIC, DARKO-Def Rebound*06:05-MAC-Change : 7 --8 --9 --10 -22 *06:02-BAR-44 - TOMIC, ANTE-Made 2P*06:00-MAC-22 - ZALMANSON, IDAN-Made 2P*05:58-BAR-11 - NAVARRO, JUAN CARLOS-Missed 2P*05:56-MAC-9 - ROTH, MORAN-Def Rebound*05:54-MAC-8 - ELIYAHU, LIOR-Missed 3P*05:51-BAR-25 - LORBEK, ERAZEM-Missed 3P*05:41-MAC-10 - PNINI, GUY-Missed 2P*05:40-MAC-10 - PNINI, GUY-Missed 2P*05:40-MAC-10 - PNINI, GUY-Missed 2P*05:38-MAC-10 - PNINI, GUY-Off Rebound*05:37-MAC-10 - PNINI, GUY-Off Rebound*05:35-MAC-10 - PNINI, GUY-Block Against*05:33-MAC-10 - PNINI, GUY-Block Against*05:31-BAR-25 - LORBEK, ERAZEM-Def Rebound*05:29-BAR-25 - LORBEK, ERAZEM-Block*05:28-BAR-25 - LORBEK, ERAZEM-Block*04:50-BAR-25 - LORBEK, ERAZEM-Made 2P*04:47-MAC-9 - ROTH, MORAN-Missed 2P*04:44-BAR-25 - LORBEK, ERAZEM-Def Rebound*04:42-BAR-25 - LORBEK, ERAZEM-Foul On*04:39-BAR-25 - LORBEK, ERAZEM-Free Throw Missed*04:38-BAR-25 - LORBEK, ERAZEM-Free Throw Made*04:35-MAC-8 - ELIYAHU, LIOR-Foul*04:33-MAC-8 - ELIYAHU, LIOR-Made 2P*04:26-BAR-11 - NAVARRO, JUAN CARLOS-Turnover*04:22-MAC-9 - ROTH, MORAN-Made 2P*03:44-BAR-11 - NAVARRO, JUAN CARLOS-Made 2P*03:40-MAC-10 - PNINI, GUY-Made 2P*03:37-BAR-25 - LORBEK, ERAZEM-Made 2P*03:34-MAC-10 - PNINI, GUY-Missed 2P*03:32-BAR-11 - NAVARRO, JUAN CARLOS-Missed 3P*03:29-MAC-22 - ZALMANSON, IDAN-Def Rebound*02:11-BAR-25 - LORBEK, ERAZEM-Made 2P*02:09-MAC-22 - ZALMANSON, IDAN-Missed 2P*02:06-BAR-24 - OLESON, BRAD-Made 3P*02:03-MAC-8 - ELIYAHU, LIOR-Missed 2P*02:02-MAC-8 - ELIYAHU, LIOR-Made 2P*02:01-MAC-8 - ELIYAHU, LIOR-Off Rebound*01:59-MAC-Time Out*01:56-BAR-Fastbreak Missed*01:55-BAR-Time Out*01:53-BAR-24 - OLESON, BRAD-Missed 2P*01:49-MAC-9 - ROTH, MORAN-Turnover*01:46-BAR-11 - NAVARRO, JUAN CARLOS-Steal*01:44-BAR-11 - NAVARRO, JUAN CARLOS-Missed 2P*01:21-BAR-Fastbreak Missed*01:18-MAC-9 - ROTH, MORAN-Def Rebound*01:16-MAC-9 - ROTH, MORAN-Missed 2P*01:14-BAR-24 - OLESON, BRAD-Def Rebound*00:37-BAR-24 - OLESON, BRAD-Made 2P*00:32-MAC-8 - ELIYAHU, LIOR-Made 2P*00:30-MAC-22 - ZALMANSON, IDAN-Assist*00:24-BAR-24 - OLESON, BRAD-Missed 2P*00:20-BAR-44 - TOMIC, ANTE-Off Rebound*00:18-BAR-44 - TOMIC, ANTE-Assist*00:12-BAR-11 - NAVARRO, JUAN CARLOS-Made 2P*00:02-MAC-9 - ROTH, MORAN-Made 3P*IV PERIOD*10:00-BAR-Change : 8 --10 -11 -25 -44 *10:00-MAC-Change : 4 --5 --7 --9 --22 *09:56-BAR-25 - LORBEK, ERAZEM-Made 2P*09:54-MAC-9 - ROTH, MORAN-Made 2P*09:51-BAR-11 - NAVARRO, JUAN CARLOS-Made 3P*09:49-MAC-4 - LOGAN, DAVID-Made 3P*09:46-BAR-44 - TOMIC, ANTE-Missed 2P*09:43-MAC-7 - HICKMAN, RICKY-Made 2P*09:40-MAC-9 - ROTH, MORAN-Assist*09:39-MAC-Fastbreak Made*08:34-BAR-Change : 8 --9 --11 -22 -44 *08:09-MAC-Change : 5 --8 --9 --12 -22 *08:05-BAR-11 - NAVARRO, JUAN CARLOS-Made 3P*08:03-MAC-12 - OHAYON, YOGEV-Missed 3P*08:02-MAC-12 - OHAYON, YOGEV-Missed 3P*08:00-MAC-12 - OHAYON, YOGEV-Off Rebound*07:57-BAR-9 - HUERTAS, MARCELINHO-Def Rebound*07:57-BAR-9 - HUERTAS, MARCELINHO-Assist*07:55-BAR-Fastbreak Made*07:53-BAR-8 - SADA, VICTOR-Made 2P*07:51-MAC-8 - ELIYAHU, LIOR-Missed 2P*07:48-MAC-8 - ELIYAHU, LIOR-Missed 2P*07:48-MAC-8 - ELIYAHU, LIOR-Made 2P*07:46-MAC-8 - ELIYAHU, LIOR-Off Rebound*07:46-MAC-8 - ELIYAHU, LIOR-Off Rebound*06:40-BAR-22 - RABASEDA, XAVIER-Missed 2P*06:37-MAC-8 - ELIYAHU, LIOR-Missed 2P*06:34-MAC-8 - ELIYAHU, LIOR-Turnover*06:33-MAC-8 - ELIYAHU, LIOR-Turnover*06:31-BAR-11 - NAVARRO, JUAN CARLOS-Turnover*06:31-BAR-11 - NAVARRO, JUAN CARLOS-Turnover*04:25-MAC-22 - ZALMANSON, IDAN-Steal*04:23-MAC-22 - ZALMANSON, IDAN-Made 2P*04:20-BAR-11 - NAVARRO, JUAN CARLOS-Made 3P*04:17-MAC-12 - OHAYON, YOGEV-Missed 2P*04:13-MAC-8 - ELIYAHU, LIOR-Made 3P*04:12-MAC-8 - ELIYAHU, LIOR-Off Rebound*04:09-BAR-22 - RABASEDA, XAVIER-Missed 3P*04:06-MAC-9 - ROTH, MORAN-Missed 3P*04:02-MAC-9 - ROTH, MORAN-Off Rebound*04:02-MAC-9 - ROTH, MORAN-Off Rebound*04:00-MAC-9 - ROTH, MORAN-Missed 3P*03:59-MAC-9 - ROTH, MORAN-Missed 3P*03:57-BAR-11 - NAVARRO, JUAN CARLOS-Def Rebound*03:56-BAR-11 - NAVARRO, JUAN CARLOS-Made 2P*03:52-MAC-8 - ELIYAHU, LIOR-Missed 2P*02:26-MAC-9 - ROTH, MORAN-Made 2P*02:07-BAR-22 - RABASEDA, XAVIER-Made 2P*02:02-MAC-22 - ZALMANSON, IDAN-Missed 2P*02:00-BAR-11 - NAVARRO, JUAN CARLOS-Made 2P*01:56-MAC-9 - ROTH, MORAN-Missed 2P*01:51-BAR-22 - RABASEDA, XAVIER-Made 3P*00:47-MAC-5 - JAMES, SHAWN-Made 2P*00:45-BAR-22 - RABASEDA, XAVIER-Missed 2P*00:43-BAR-22 - RABASEDA, XAVIER-Off Rebound*00:39-BAR-9 - HUERTAS, MARCELINHO-Missed 2P*00:37-MAC-9 - ROTH, MORAN-Def Rebound*00:24-MAC-9 - ROTH, MORAN-Missed 3P*00:20-MAC-12 - OHAYON, YOGEV-Off Rebound*00:17-MAC-12 - OHAYON, YOGEV-Missed 2P*00:14-BAR-22 - RABASEDA, XAVIER-Def Rebound*00:10-BAR-22 - RABASEDA, XAVIER-Assist*00:02-BAR-44 - TOMIC, ANTE-Made 2P*</EventSText>
  </Event>
</HomeStats>